payload_discovery/__init__.py
payload_discovery/compiler.py
payload_discovery/core.py
payload_discovery/heaven_pis_integration.py
payload_discovery/mcp_server.py
payload_discovery/mcp_server_v2.py
payload_discovery/mcp_server_v2.py.backup
payload_discovery/mcp_tool.py
payload_discovery-0.1.6.dist-info/METADATA
payload_discovery-0.1.6.dist-info/WHEEL
payload_discovery-0.1.6.dist-info/entry_points.txt
payload_discovery-0.1.6.dist-info/RECORD
