Metadata-Version: 2.4
Name: payload-discovery
Version: 0.1.6
Summary: System for creating numbered instruction sequences for agent consumption
Author: HEAVEN Team
Requires-Python: >=3.9
Requires-Dist: fastmcp>=2.0.0
Requires-Dist: mcp>=1.0.0
Requires-Dist: pydantic-settings>=2.0.0
Requires-Dist: pydantic-stack-core>=0.1.0
Requires-Dist: pydantic>=2.0.0
Requires-Dist: starlog-mcp
Provides-Extra: dev
Requires-Dist: black>=23.0.0; extra == 'dev'
Requires-Dist: pytest-asyncio>=0.21.0; extra == 'dev'
Requires-Dist: pytest>=7.0.0; extra == 'dev'
Requires-Dist: ruff>=0.1.0; extra == 'dev'
